{
	"info": {
		"_postman_id": "c08cbd6b-f923-411b-84c2-b4c2e587a152",
		"name": "categoriasAPI",
		"schema": "https://schema.getpostman.com/json/collection/v2.1.0/collection.json",
		"_exporter_id": "29860203"
	},
	"item": [
		{
			"name": "index",
			"request": {
				"method": "GET",
				"header": [],
				"url": {
					"raw": "http://localhost:8000/api/categorias",
					"protocol": "http",
					"host": [
						"localhost"
					],
					"port": "8000",
					"path": [
						"api",
						"categorias"
					]
				}
			},
			"response": []
		},
		{
			"name": "store",
			"request": {
				"method": "POST",
				"header": [],
				"url": {
					"raw": "http://localhost:8000/api/categorias",
					"protocol": "http",
					"host": [
						"localhost"
					],
					"port": "8000",
					"path": [
						"api",
						"categorias"
					]
				}
			},
			"response": []
		},
		{
			"name": "update",
			"request": {
				"method": "PUT",
				"header": [],
				"url": {
					"raw": "http://localhost:8000/api/categorias/1",
					"protocol": "http",
					"host": [
						"localhost"
					],
					"port": "8000",
					"path": [
						"api",
						"categorias",
						"1"
					]
				}
			},
			"response": []
		},
		{
			"name": "New Request",
			"request": {
				"method": "DELETE",
				"header": [],
				"url": {
					"raw": "http://localhost:8000/api/categorias/1",
					"protocol": "http",
					"host": [
						"localhost"
					],
					"port": "8000",
					"path": [
						"api",
						"categorias",
						"1"
					]
				}
			},
			"response": []
		},
		{
			"name": "show",
			"request": {
				"method": "GET",
				"header": [],
				"url": {
					"raw": "http://localhost:8000/api/categorias/1",
					"protocol": "http",
					"host": [
						"localhost"
					],
					"port": "8000",
					"path": [
						"api",
						"categorias",
						"1"
					]
				}
			},
			"response": []
		}
	]
}